ib_wrapper/__init__.py
ib_wrapper/cli.py
ib_wrapper/ib_wrapper.py
ib_wrapper-0.1.0.dist-info/METADATA
ib_wrapper-0.1.0.dist-info/RECORD
ib_wrapper-0.1.0.dist-info/WHEEL
ib_wrapper-0.1.0.dist-info/entry_points.txt
ib_wrapper-0.1.0.dist-info/top_level.txt
