Metadata-Version: 2.1
Name: ib-wrapper
Version: 0.1.0
Summary: Dynamic runtime TWS IB API for python
Home-page: https://github.com/asteriogonzalez/ib_wrapper
Author: Asterio
Author-email: asterio.gonzalez@gmail.com
License: MIT license
Keywords: ib_wrapper
Platform: UNKNOWN
Classifier: Development Status :: 2 - Pre-Alpha
Classifier: Intended Audience :: Developers
Classifier: License :: OSI Approved :: MIT License
Classifier: Natural Language :: English
Classifier: Programming Language :: Python :: 2
Classifier: Programming Language :: Python :: 2.7
Classifier: Programming Language :: Python :: 3
Classifier: Programming Language :: Python :: 3.4
Classifier: Programming Language :: Python :: 3.5
Classifier: Programming Language :: Python :: 3.6
Classifier: Programming Language :: Python :: 3.7
Requires-Dist: Click (>=6.0)
